torchmetal/__init__.py
torchmetal/datasets/__init__.py
torchmetal/datasets/assets/cifar100/cifar-fs/test.json
torchmetal/datasets/assets/cifar100/cifar-fs/train.json
torchmetal/datasets/assets/cifar100/cifar-fs/val.json
torchmetal/datasets/assets/cifar100/fc100/test.json
torchmetal/datasets/assets/cifar100/fc100/train.json
torchmetal/datasets/assets/cifar100/fc100/val.json
torchmetal/datasets/assets/cub/test.json
torchmetal/datasets/assets/cub/train.json
torchmetal/datasets/assets/cub/val.json
torchmetal/datasets/assets/doublemnist/test.json
torchmetal/datasets/assets/doublemnist/train.json
torchmetal/datasets/assets/doublemnist/val.json
torchmetal/datasets/assets/omniglot/test.json
torchmetal/datasets/assets/omniglot/train.json
torchmetal/datasets/assets/omniglot/val.json
torchmetal/datasets/assets/tcga/cancers.json
torchmetal/datasets/assets/tcga/task_variables.json
torchmetal/datasets/assets/tcga/test.json
torchmetal/datasets/assets/tcga/train.json
torchmetal/datasets/assets/tcga/val.json
torchmetal/datasets/assets/triplemnist/test.json
torchmetal/datasets/assets/triplemnist/train.json
torchmetal/datasets/assets/triplemnist/val.json
torchmetal/datasets/cifar100/__init__.py
torchmetal/datasets/cifar100/base.py
torchmetal/datasets/cifar100/cifar_fs.py
torchmetal/datasets/cifar100/fc100.py
torchmetal/datasets/cub.py
torchmetal/datasets/doublemnist.py
torchmetal/datasets/helpers.py
torchmetal/datasets/miniimagenet.py
torchmetal/datasets/omniglot.py
torchmetal/datasets/pascal5i.py
torchmetal/datasets/tcga.py
torchmetal/datasets/tieredimagenet.py
torchmetal/datasets/triplemnist.py
torchmetal/datasets/utils.py
torchmetal/modules/__init__.py
torchmetal/modules/activation.py
torchmetal/modules/batchnorm.py
torchmetal/modules/container.py
torchmetal/modules/conv.py
torchmetal/modules/linear.py
torchmetal/modules/module.py
torchmetal/modules/normalization.py
torchmetal/modules/parallel.py
torchmetal/modules/sparse.py
torchmetal/toy/__init__.py
torchmetal/toy/harmonic.py
torchmetal-0.1.0.dist-info/LICENSE
torchmetal-0.1.0.dist-info/WHEEL
torchmetal-0.1.0.dist-info/METADATA
torchmetal-0.1.0.dist-info/RECORD
