Metadata-Version: 2.1
Name: torchmetal
Version: 0.1.0
Summary: A library for Meta-Learning and Few-Shot Learning with PyTorch
Home-page: https://github.com/sevro/torchmetal
License: MIT
Keywords: meta-learning,pytorch,few-shot,few-shot,learning
Author: Tristan Deleu
Author-email: tristan.deleu@gmail.com
Maintainer: Derek Goddeau
Maintainer-email: derek.j.goddeau@pm.me
Requires-Python: >=3.6.2,<4.0.0
Classifier: Development Status :: 4 - Beta
Classifier: Intended Audience :: Science/Research
Classifier: License :: OSI Approved :: MIT License
Classifier: Programming Language :: Python :: 3
Classifier: Programming Language :: Python :: 3.6
Classifier: Programming Language :: Python :: 3.7
Classifier: Programming Language :: Python :: 3.8
Classifier: Programming Language :: Python :: 3.9
Classifier: Topic :: Scientific/Engineering :: Artificial Intelligence
Provides-Extra: tcga
Requires-Dist: academictorrents (>=2.1.0,<2.2.0); extra == "tcga"
Requires-Dist: h5py
Requires-Dist: numpy (>=1.14.0)
Requires-Dist: ordered-set
Requires-Dist: pandas (>=0.24.0,<0.25.0); extra == "tcga"
Requires-Dist: pillow (>=7.0.0)
Requires-Dist: requests
Requires-Dist: six (>=1.11.0,<1.12.0); extra == "tcga"
Requires-Dist: torch (>=1.4.0,<1.9.0)
Requires-Dist: torchvision (>=0.5.0,<0.10.0)
Requires-Dist: tqdm (>=4.0.0)
Project-URL: Documentation, https://github.com/sevro/torchmetal
Project-URL: Repository, https://github.com/sevro/torchmetal
